ezFreeCAD
