Metadata-Version: 1.0
Name: ezFreeCAD
Version: 0.13
Summary: Python wrapper for interfacing with FreeCAD it make it easier to draw 3D objects programmatically
Home-page: https://github.com/AFMD/ezFreeCAD
Author: Grey Christoforo
Author-email: grey@mylastname.net
License: GNUGPLv2
Platform: UNKNOWN
